agenzic/__init__.py
agenzic/__main__.py
agenzic/commands/__init__.py
agenzic/commands/ask.py
agenzic/commands/codegen.py
agenzic/commands/codemetrics.py
agenzic/commands/commit.py
agenzic/commands/inspect.py
agenzic/commands/projtree.py
agenzic/commands/review.py
agenzic/commands/summarize.py
agenzic/commands/tests.py
agenzic/commands/experimental/__init__.py
agenzic/commands/experimental/docgen.py
agenzic/commands/experimental/graph.py
agenzic/commands/experimental/inception.py
agenzic/commands/experimental/myflow.py
agenzic/utils/__init__.py
agenzic/utils/ai_client.py
agenzic/utils/helpers.py
agenzic-0.1.2.dist-info/licenses/LICENSE
agenzic-0.1.2.dist-info/METADATA
agenzic-0.1.2.dist-info/WHEEL
agenzic-0.1.2.dist-info/entry_points.txt
agenzic-0.1.2.dist-info/top_level.txt
agenzic-0.1.2.dist-info/RECORD
