Metadata-Version: 2.4
Name: agenzic
Version: 0.1.2
Summary: AI-powered CLI assistant for developers: commits, summaries, PR reviews, docs.
Author: Ratul Dash
License: MIT License
Keywords: ai,cli,developer-tools,commit,review,summarize,docs,tests
Classifier: Development Status :: 3 - Alpha
Classifier: Intended Audience :: Developers
Classifier: Topic :: Software Development :: Build Tools
Classifier: License :: OSI Approved :: MIT License
Classifier: Programming Language :: Python :: 3
Classifier: Programming Language :: Python :: 3.11
Classifier: Operating System :: OS Independent
Requires-Python: >=3.11
License-File: LICENSE
Requires-Dist: dotenv>=0.9.9
Requires-Dist: radon>=6.0.1
Requires-Dist: requests>=2.31.0
Requires-Dist: typer>=0.19.0
Dynamic: license-file
